pythoshop/__init__.py
pythoshop/adjust_brightness.py
pythoshop/apply_filter.py
pythoshop/resize_image.py
pythoshop/transform_image.py
pythoshop-3.2.22.dist-info/LICENSE
pythoshop-3.2.22.dist-info/METADATA
pythoshop-3.2.22.dist-info/WHEEL
pythoshop-3.2.22.dist-info/RECORD
