Metadata-Version: 2.1
Name: pythoshop
Version: 3.2.22
Summary: A Python version of Photoshop where users can do simple tasks of photo editing, such as croopping an image, rescaling an image, applying filters to an image, and much more.
License: MIT
Author: Salva Umar, Jenny Lee, Ella Hein, Rachel Li
Requires-Python: >=3.9
Classifier: License :: OSI Approved :: MIT License
Classifier: Programming Language :: Python :: 3
Classifier: Programming Language :: Python :: 3.9
Classifier: Programming Language :: Python :: 3.10
Classifier: Programming Language :: Python :: 3.11
Classifier: Programming Language :: Python :: 3.12
Requires-Dist: matplotlib (>=3.8.2)
